Workbook

Sheet Deal Overview
A1: REAL ESTATE DEAL ANALYSIS TOOLKIT
A2: Instructions: Fill in YELLOW cells with property details. Blue cells auto-calculate. Review all tabs for complete analysis.
A4: PROPERTY DETAILS
A5: Address: | D5: Year Built:
A6: Type: | D6: Bedrooms:
A7: Square Feet: | D7: Bathrooms:
A8: Lot Size:
A10: KEY FINANCIAL INPUTS
A11: Purchase Price: | B11: 250000 | D11: Monthly Rent: | E11: 2500
A12: ARV: | B12: 350000 | D12: Annual Tax: | E12: 3000
A13: Rehab Budget: | B13: 50000 | D13: Annual Insurance: | E13: 1200
A14: Closing Costs: | B14: 7500 | D14: Monthly HOA: | E14: 0
A16: QUICK SUMMARY METRICS
A17: Metric | B17: Value | C17: Metric | D17: Value
A18: Total Investment: | B18: =B11+B13+B14 | C18: Potential Equity: | D18: =B12-B18
A19: Equity %: | B19: =(B12-B18)/B12 | C19: Annual Gross Rent: | D19: =E11*12
A20: Monthly Gross Yield: | B20: =E11/B18 | C20: Est. Cap Rate: | D20: =(E11*12-E12-E13-E14*12)/B18
A22: DEAL QUALITY INDICATORS
A23: Equity Spread: | B23: =IF(D18>50000, "EXCELLENT", IF(D18>25000, "GOOD", IF(D18>0, "FAIR", "POOR"))) | C23: Cap Rate: | D23: =IF(D20>0.08, "EXCELLENT", IF(D20>0.06, "GOOD", IF(D20>0.04, "FAIR", "POOR")))

Sheet Scenario Breakdown
A1: SCENARIO BREAKDOWN - Compare Multiple Exit Strategies
A2: Yellow cells = Your Input | Blue cells = Calculated | Compare scenarios side-by-side
A4: Input Parameter | B4: WHOLESALE | C4: FIX & FLIP | D4: BUY & HOLD | E4: SELLER FINANCE
A5: ACQUISITION
A6: Purchase Price | B6: ='Deal Overview'!B11 | C6: ='Deal Overview'!B11 | D6: ='Deal Overview'!B11 | E6: ='Deal Overview'!B11
A7: ARV | B7: ='Deal Overview'!B12 | C7: ='Deal Overview'!B12 | D7: ='Deal Overview'!B12 | E7: ='Deal Overview'!B12
A8: Assignment Fee % | B8: 0.05
A10: REHAB & COSTS
A11: Rehab Budget | B11: 0 | C11: ='Deal Overview'!B13 | D11: 10000 | E11: 5000
A12: Closing Costs (Buy) | B12: 3000 | C12: ='Deal Overview'!B14 | D12: ='Deal Overview'!B14 | E12: ='Deal Overview'!B14
A13: Holding Costs (months) | B13: 0 | C13: 6 | D13: 0 | E13: 0
A14: Monthly Holding Cost | B14: 0 | C14: 1500 | D14: 0 | E14: 0
A15: Selling Costs % | B15: 0.01 | C15: 0.08 | D15: 0 | E15: 0
A17: FINANCING
A18: Down Payment % | B18: 0 | C18: 0.2 | D18: 0.25 | E18: 0.1
A19: Loan Interest Rate | B19: 0 | C19: 0.075 | D19: 0.07 | E19: 0.06
A20: Loan Term (years) | B20: 0 | C20: 0.5 | D20: 30 | E20: 15
A22: RENTAL INCOME
A23: Monthly Rent | B23: 0 | C23: 0 | D23: ='Deal Overview'!E11 | E23: ='Deal Overview'!E11
A24: Vacancy Rate | B24: 0 | C24: 0 | D24: 0.08 | E24: 0.05
A26: CALCULATED RESULTS
A27: Total Cash Needed | B27: =B6+B12+B13 | C27: =C6+C12+C13+(C14*C15) | D27: =D6+D12+D13 | E27: =E6+E12+E13
A28: Loan Amount | B28: =0 | C28: =C6*(1-C19) | D28: =D6*(1-D19) | E28: =E6*(1-E19)
A29: Net Profit/Sale | B29: =B7*B8 | C29: =(C7-(C12+C14*C15+C7*C16)) | D29: =0 | E29: =0
A30: Annual Cash Flow | B30: =0 | C30: =0 | D30: =(D23*(1-D24)*12)-(D26*12) | E30: =(E23*(1-E24)*12)-(E26*12)
A31: Cash-on-Cash Return | B31: =B29/B27 | C31: =C29/C27 | D31: =D30/D27 | E31: =E30/E27
A32: ROI | B32: =B29/B27 | C32: =C29/C27 | D32: =(D7-D27)/D27 | E32: =(E7-E27)/E27

Sheet Performance Metrics
A1: PERFORMANCE METRICS & EXIT STRATEGY COMPARISON
A3: Strategy | B3: Total Investment | C3: Net Return | D3: ROI % | E3: Timeline | F3: Risk Level
A4: Wholesale | B4: ='Scenario Breakdown'!B27 | C4: ='Scenario Breakdown'!B29 | D4: ='Scenario Breakdown'!B31 | E4: 0-30 days | F4: Low
A5: Fix & Flip | B5: ='Scenario Breakdown'!C27 | C5: ='Scenario Breakdown'!C29 | D5: ='Scenario Breakdown'!C31 | E5: 3-6 months | F5: Medium
A6: Buy & Hold | B6: ='Scenario Breakdown'!D27 | C6: ='Scenario Breakdown'!D30 | D6: ='Scenario Breakdown'!D32 | E6: 5+ years | F6: Low-Med
A7: Seller Finance | B7: ='Scenario Breakdown'!E27 | C7: ='Scenario Breakdown'!E30 | D7: ='Scenario Breakdown'!E32 | E7: Variable | F7: Medium
A10: ADVANCED METRICS (Buy & Hold Focus)
A11: Debt Coverage Ratio (DCR) | B11: =('Scenario Breakdown'!D23*(1-'Scenario Breakdown'!D24)*12)/('Scenario Breakdown'!D26*12)
A12: Break-Even Rent | B12: =('Scenario Breakdown'!D26+'Deal Overview'!E12/12+'Deal Overview'!E13/12+'Deal Overview'!E14)/(1-'Scenario Breakdown'!D24)
A13: Gross Rent Multiplier | B13: ='Deal Overview'!B11/('Deal Overview'!E11*12)
A14: Capitalization Rate | B14: ='Deal Overview'!D20

Sheet What-If Analysis
A1: WHAT-IF SENSITIVITY ANALYSIS
A2: Test different scenarios by adjusting yellow input cells. See immediate impact on returns.
A4: RENT SENSITIVITY ANALYSIS
A5: Monthly Rent Scenario | B5: Annual NOI | C5: Cash Flow | D5: Cash-on-Cash | E5: Cap Rate
A6: Base Rent -20% | B6: =='Deal Overview'!E11*0.8*12-'Deal Overview'!E12-'Deal Overview'!E13-'Deal Overview'!E14*12 | C6: =B6-'Scenario Breakdown'!D26*12 | D6: =C6/('Scenario Breakdown'!D27) | E6: =B6/'Deal Overview'!B11
A7: Base Rent -10% | B7: =='Deal Overview'!E11*0.9*12-'Deal Overview'!E12-'Deal Overview'!E13-'Deal Overview'!E14*12 | C7: =B7-'Scenario Breakdown'!D26*12 | D7: =C7/('Scenario Breakdown'!D27) | E7: =B7/'Deal Overview'!B11
A8: Current Base Rent | B8: =='Deal Overview'!E11*1.0*12-'Deal Overview'!E12-'Deal Overview'!E13-'Deal Overview'!E14*12 | C8: =B8-'Scenario Breakdown'!D26*12 | D8: =C8/('Scenario Breakdown'!D27) | E8: =B8/'Deal Overview'!B11
A9: Base Rent +10% | B9: =='Deal Overview'!E11*1.1*12-'Deal Overview'!E12-'Deal Overview'!E13-'Deal Overview'!E14*12 | C9: =B9-'Scenario Breakdown'!D26*12 | D9: =C9/('Scenario Breakdown'!D27) | E9: =B9/'Deal Overview'!B11
A10: Base Rent +20% | B10: =='Deal Overview'!E11*1.2*12-'Deal Overview'!E12-'Deal Overview'!E13-'Deal Overview'!E14*12 | C10: =B10-'Scenario Breakdown'!D26*12 | D10: =C10/('Scenario Breakdown'!D27) | E10: =B10/'Deal Overview'!B11
A12: INTEREST RATE SENSITIVITY
A13: Interest Rate | B13: Monthly Payment | C13: Annual Debt Service | D13: Cash Flow | E13: DCR
A14: 4.5% | B14: =='Scenario Breakdown'!D28*(0.045/12*POWER(1+0.045/12,='Scenario Breakdown'!D21*12))/(POWER(1+0.045/12,='Scenario Breakdown'!D21*12)-1) | C14: =B14*12 | D14: ='Deal Overview'!E11*12-'Deal Overview'!E12-'Deal Overview'!E13-'Deal Overview'!E14*12-C14 | E14: =('Deal Overview'!E11*12-'Deal Overview'!E12-'Deal Overview'!E13-'Deal Overview'!E14*12)/C14
A15: 5.5% | B15: =='Scenario Breakdown'!D28*(0.055/12*POWER(1+0.055/12,='Scenario Breakdown'!D21*12))/(POWER(1+0.055/12,='Scenario Breakdown'!D21*12)-1) | C15: =B15*12 | D15: ='Deal Overview'!E11*12-'Deal Overview'!E12-'Deal Overview'!E13-'Deal Overview'!E14*12-C15 | E15: =('Deal Overview'!E11*12-'Deal Overview'!E12-'Deal Overview'!E13-'Deal Overview'!E14*12)/C15
A16: 6.5% | B16: =='Scenario Breakdown'!D28*(0.065/12*POWER(1+0.065/12,='Scenario Breakdown'!D21*12))/(POWER(1+0.065/12,='Scenario Breakdown'!D21*12)-1) | C16: =B16*12 | D16: ='Deal Overview'!E11*12-'Deal Overview'!E12-'Deal Overview'!E13-'Deal Overview'!E14*12-C16 | E16: =('Deal Overview'!E11*12-'Deal Overview'!E12-'Deal Overview'!E13-'Deal Overview'!E14*12)/C16
A17: 7.5% | B17: =='Scenario Breakdown'!D28*(0.075/12*POWER(1+0.075/12,='Scenario Breakdown'!D21*12))/(POWER(1+0.075/12,='Scenario Breakdown'!D21*12)-1) | C17: =B17*12 | D17: ='Deal Overview'!E11*12-'Deal Overview'!E12-'Deal Overview'!E13-'Deal Overview'!E14*12-C17 | E17: =('Deal Overview'!E11*12-'Deal Overview'!E12-'Deal Overview'!E13-'Deal Overview'!E14*12)/C17
A18: 8.5% | B18: =='Scenario Breakdown'!D28*(0.085/12*POWER(1+0.085/12,='Scenario Breakdown'!D21*12))/(POWER(1+0.085/12,='Scenario Breakdown'!D21*12)-1) | C18: =B18*12 | D18: ='Deal Overview'!E11*12-'Deal Overview'!E12-'Deal Overview'!E13-'Deal Overview'!E14*12-C18 | E18: =('Deal Overview'!E11*12-'Deal Overview'!E12-'Deal Overview'!E13-'Deal Overview'!E14*12)/C18
A20: VACANCY RATE IMPACT
A21: Vacancy Rate | B21: Effective Annual Rent | C21: Annual Cash Flow | D21: Impact vs 0%
A22: 0% (Optimistic) | B22: ='Deal Overview'!E11*12*(1-0.0) | C22: =B22-'Deal Overview'!E12-'Deal Overview'!E13-'Deal Overview'!E14*12-'Scenario Breakdown'!D26*12 | D22: =C22-C18
A23: 5% (Good) | B23: ='Deal Overview'!E11*12*(1-0.05) | C23: =B23-'Deal Overview'!E12-'Deal Overview'!E13-'Deal Overview'!E14*12-'Scenario Breakdown'!D26*12 | D23: =C23-C19
A24: 8% (Average) | B24: ='Deal Overview'!E11*12*(1-0.08) | C24: =B24-'Deal Overview'!E12-'Deal Overview'!E13-'Deal Overview'!E14*12-'Scenario Breakdown'!D26*12 | D24: =C24-C20
A25: 10% (Conservative) | B25: ='Deal Overview'!E11*12*(1-0.1) | C25: =B25-'Deal Overview'!E12-'Deal Overview'!E13-'Deal Overview'!E14*12-'Scenario Breakdown'!D26*12 | D25: =C25-C21
A26: 15% (Poor) | B26: ='Deal Overview'!E11*12*(1-0.15) | C26: =B26-'Deal Overview'!E12-'Deal Overview'!E13-'Deal Overview'!E14*12-'Scenario Breakdown'!D26*12 | D26: =C26-C22

Sheet Risk & Expense Analysis
A1: RISK & EXPENSE ANALYSIS
A3: MONTHLY OPERATING EXPENSES
A4: Expense Category | B4: Monthly Amount | C4: Annual Amount | D4: % of Rent
A5: Property Tax | B5: ='Deal Overview'!E12/12 | C5: ='Deal Overview'!E12 | D5: =B5/'Deal Overview'!E11
A6: Insurance | B6: ='Deal Overview'!E13/12 | C6: ='Deal Overview'!E13 | D6: =B6/'Deal Overview'!E11
A7: HOA/Condo Fees | B7: ='Deal Overview'!E14 | C7: ='Deal Overview'!E14*12 | D7: =B7/'Deal Overview'!E11
A8: Property Management (8%) | B8: ='Deal Overview'!E11*0.08 | C8: ='Deal Overview'!E11*0.08*12 | D8: =B8/'Deal Overview'!E11
A9: Maintenance Reserve (5%) | B9: ='Deal Overview'!E11*0.05 | C9: ='Deal Overview'!E11*0.05*12 | D9: =B9/'Deal Overview'!E11
A10: Vacancy Reserve (8%) | B10: ='Deal Overview'!E11*0.08 | C10: ='Deal Overview'!E11*0.08*12 | D10: =B10/'Deal Overview'!E11
A11: CapEx Reserve (5%) | B11: ='Deal Overview'!E11*0.05 | C11: ='Deal Overview'!E11*0.05*12 | D11: =B11/'Deal Overview'!E11
A12: Utilities (if owner-paid) | B12: 0 | C12: 0 | D12: =B12/'Deal Overview'!E11
A13: Lawn/Snow/Pest | B13: 100 | C13: 1200 | D13: =B13/'Deal Overview'!E11
A14: TOTAL MONTHLY EXPENSES | B14: =SUM(B5:B13) | C14: =SUM(C5:C13) | D14: =B14/'Deal Overview'!E11
A16: RECOMMENDED CASH RESERVES
A17: Reserve Type | B17: Months | C17: Amount Needed
A18: Operating Reserve | B18: 6 | C18: =B7*6
A19: CapEx Reserve | B19: 12 | C19: ='Deal Overview'!E11*0.05*12
A20: Vacancy Buffer | B20: 3 | C20: ='Deal Overview'!E11*3
A21: TOTAL RESERVES | C21: =SUM(C18:C20)
A23: RISK SCORE CALCULATOR
A24: Risk Factor | B24: Current Value | C24: Risk Level | D24: Weight | E24: Score
A25: Loan-to-Value (LTV) | B25: ='Scenario Breakdown'!D28/'Deal Overview'!B12 | C25: =IF(B{row}<0.65,"Low",IF(B{row}<0.80,"Medium","High")) | D25: 0.35 | E25: =IF(C25="Low",1,IF(C25="Medium",5,9))*D25
A26: Debt Coverage Ratio | B26: =('Deal Overview'!E11*12-'Deal Overview'!E12-'Deal Overview'!E13)/('Scenario Breakdown'!D26*12) | C26: =IF(B26>1.25,"Low",IF(B26>1.0,"Medium","High")) | D26: 0.3 | E26: =IF(C26="Low",1,IF(C26="Medium",5,9))*D26
A27: Cash Reserves/PITI | B27: =C20/B10 | C27: =IF(B27>6,"Low",IF(B27>3,"Medium","High")) | D27: 0.2 | E27: =IF(C27="Low",1,IF(C27="Medium",5,9))*D27
A28: Expense Ratio | B28: =D11 | C28: =IF(B28<0.45,"Low",IF(B28<0.55,"Medium","High")) | D28: 0.15 | E28: =IF(C28="Low",1,IF(C28="Medium",5,9))*D28
A29: OVERALL RISK SCORE | E29: =SUM(E25:E28)
A30: RISK RATING | E30: =IF(E29<3,"LOW RISK",IF(E29<6,"MODERATE RISK","HIGH RISK"))
